Workbook

Sheet 00_ReadMe
A1: Research Workbook — Supply Chain Control Tower Dashboard (Project 1)
A3: Purpose | B3: A single, auditable workbook that records the literature search, screening, extraction, data cleaning, analysis, and the formula library for Project 1. The structure repeats for the other four projects.
A4: How sheets connect | B4: Search log feeds the screening log. The screening log feeds the extraction table. The extraction table feeds the PRISMA, bibliometric, and N gram sheets. The analysis sheet holds the live KPI engine. The final summary links the key numbers.
A5: Colour legend | B5: Blue text marks a hardcoded input that a user may change. Black text marks a formula. Green text marks a link that pulls from another sheet.
A6: Live formulas | B6: Cells with formulas recalculate when the source data changes. The analysis sheet runs on an illustrative sample. Replace the sample with the cleaned DataCo extract and every KPI updates.
A7: Excel 365 functions | B7: XLOOKUP, UNIQUE, FILTER, and LET are shown on the formula sheet as exact syntax for Excel 365. Live demonstration cells use INDEX MATCH and COUNTIFS so the workbook returns values in every spreadsheet engine.
A8: Verification | B8: Each reference was checked against a primary source during research. The references sheet records the verification status and the link.
A9: Author | B9: Rupal Rani. Tata Institute of Social Sciences, Mumbai.

Sheet 01_Search_Log
A1: Search Log
A2: Record of literature searches. For a formal review these queries map to Scopus, Web of Science, and Crossref. Queries below were run during live research for this project.
A3: No | B3: Date | C3: Source / engine | D3: Search query | E3: Filters | F3: Hits (approx) | G3: Used | H3: Notes
A4: 1 | B4: 2026-05-30 | C4: Scholar / publisher | D4: supply chain control tower concept end-to-end visibility | E4: none | F4: 9 | G4: Y | H4: Concept and definition
A5: 2 | B5: 2026-05-30 | C5: Scholar / publisher | D5: big data analytics supply chain management review | E5: peer reviewed | F5: 8 | G5: Y | H5: Waller and Fawcett; Nguyen et al.
A6: 3 | B6: 2026-05-30 | C6: Scholar / publisher | D6: supply chain resilience COVID-19 ripple effect Ivanov | E6: 2019-2021 | F6: 7 | G6: Y | H6: Ivanov 2020 simulation
A7: 4 | B7: 2026-05-30 | C7: Scholar / publisher | D7: supply chain performance SCOR KPI Gunasekaran | E7: none | F7: 8 | G7: Y | H7: Performance metrics frameworks
A8: 5 | B8: 2026-05-30 | C8: Kaggle / Mendeley | D8: DataCo smart supply chain dataset; Olist e-commerce | E8: datasets | F8: 10 | G8: Y | H8: Primary and alternative data
A9: 6 | B9: 2026-05-30 | C9: Scholar / publisher | D9: big data analytics supply chain state-of-the-art review 2018 | E9: Computers & OR | F9: 9 | G9: Y | H9: Nguyen et al. 2018 confirmed
A10: 7 | B10: 2026-05-30 | C10: Scholar / publisher | D10: Ivanov epidemic outbreaks global supply chains TRE 2020 | E10: TRE | F10: 7 | G10: Y | H10: Article 101922 confirmed
A11: 8 | B11: 2026-05-30 | C11: World Bank / PIB | D11: World Bank LPI 2023 India rank Connecting to Compete | E11: official | F11: 7 | G11: Y | H11: India rank 38 of 139
A12: 9 | B12: 2026-05-30 | C12: DPIIT / Invest India | D12: National Logistics Policy 2022 logistics cost GDP Gati Shakti | E12: official | F12: 9 | G12: Y | H12: Cost target 7.5 to 8 percent
A13: 10 | B13: 2026-05-30 | C13: Publisher | D13: Stephen Few information dashboard design principles | E13: books | F13: 9 | G13: Y | H13: Dashboard design reference
A14: 11 | B14: 2026-05-30 | C14: Scholar / publisher | D14: digital supply chain twin IoT Ivanov Dolgui 2021 | E14: peer reviewed | F14: 9 | G14: Y | H14: Digital twin PPC 2021
A15: 12 | B15: 2026-05-30 | C15: Scholar / publisher | D15: supply chain visibility agility Brusset Barratt Oke | E15: peer reviewed | F15: 8 | G15: Y | H15: Visibility and agility
... A23: 20 | B23: 2026-05-30 | C23: Web | D23: general logistics blogs and secondary posts | E23: none | F23: 30 | G23: N | H23: Excluded as non primary
C25: Total searches | F25: =COUNTA(A4:A23) -> 20
C26: Searches used | F26: =COUNTIF(G4:G23,"Y") -> 19

Sheet 02_Screening_Log
A1: Screening Log
A2: Title and abstract screening with the include or exclude decision and the reason. Included records carry forward to the extraction table.
A3: RecID | B3: Short citation | C3: Year | D3: Source type | E3: Title relevant | F3: Abstract relevant | G3: Decision | H3: Exclusion reason
A4: 1 | B4: Lee, Padmanabhan & Whang | C4: 1997 | D4: Journal | E4: Y | F4: Y | G4: Include
A5: 2 | B5: Gunasekaran, Patel & Tirtiroglu | C5: 2001 | D5: Journal | E5: Y | F5: Y | G5: Include
A6: 3 | B6: Barratt & Oke | C6: 2007 | D6: Journal | E6: Y | F6: Y | G6: Include
A7: 4 | B7: Waller & Fawcett | C7: 2013 | D7: Journal | E7: Y | F7: Y | G7: Include
A8: 5 | B8: Few | C8: 2013 | D8: Book | E8: Y | F8: Y | G8: Include
A9: 6 | B9: Brusset | C9: 2016 | D9: Journal | E9: Y | F9: Y | G9: Include
A10: 7 | B10: Wang, Gunasekaran, Ngai & Papadopoulos | C10: 2016 | D10: Journal | E10: Y | F10: Y | G10: Include
A11: 8 | B11: APICS SCOR v12.0 | C11: 2017 | D11: Standard | E11: Y | F11: Y | G11: Include
A12: 9 | B12: Trzuskawska-Grzesinska | C12: 2017 | D12: Journal | E12: Y | F12: Y | G12: Include
A13: 10 | B13: Buyukozkan & Gocer | C13: 2018 | D13: Journal | E13: Y | F13: Y | G13: Include
A14: 11 | B14: Nguyen, Zhou, Spiegler, Ieromonachou & Lin | C14: 2018 | D14: Journal | E14: Y | F14: Y | G14: Include
A15: 12 | B15: Olist e-commerce dataset | C15: 2018 | D15: Dataset | E15: Y | F15: Y | G15: Include
... A25: 22 | B25: World Bank LPI | C25: 2023 | D25: Report | E25: Y | F25: Y | G25: Include
A26: 23 | B26: Generic SCM vendor blog post | C26: 2024 | D26: Web | E26: N | F26: N | G26: Exclude | H26: Non primary source
A27: 24 | B27: Duplicate of Nguyen et al. (repository copy) | C27: 2018 | D27: Repository | E27: Y | F27: Y | G27: Exclude | H27: Duplicate record
A28: 25 | B28: Student class project on Medium | C28: 2023 | D28: Web | E28: Y | F28: N | G28: Exclude | H28: Not peer reviewed
A29: 26 | B29: Predatory journal SCM article | C29: 2021 | D29: Journal | E29: Y | F29: N | G29: Exclude | H29: Source quality concern
A30: 27 | B30: Pure marketing white paper | C30: 2022 | D30: Web | E30: N | F30: N | G30: Exclude | H30: Promotional, no method
A31: 28 | B31: Off topic finance ripple study | C31: 2020 | D31: Journal | E31: Y | F31: N | G31: Exclude | H31: Out of scope
B33: Included | G33: =COUNTIF(G4:G31,"Include") -> 22
B34: Excluded | G34: =COUNTIF(G4:G31,"Exclude") -> 6

Sheet 03_Extraction
A1: Extraction Table (included studies)
A2: One row per included source. Year, Level, and Type drive the bibliometric counts. Verified records the primary source check.
A3: Key | B3: Authors / issuer | C3: Year | D3: Level | E3: Type | F3: Method / focus | G3: Key finding (short) | H3: KPI relevance | I3: Verified | J3: Link / DOI
A4: Lee 1997 | B4: Lee, Padmanabhan & Whang | C4: 1997 | D4: Global | E4: Journal | F4: Analytical model | G4: Information distortion creates the bullwhip effect | H4: Demand and order variance | I4: Y | J4: 10.1287/mnsc.43.4.546
A5: Gunasekaran 2001 | B5: Gunasekaran, Patel & Tirtiroglu | C5: 2001 | D5: Global | E5: Journal | F5: Framework | G5: KPI framework across plan, source, make, deliver | H5: KPI design | I5: Y | J5: IJOPM 21(1/2)
A6: Barratt 2007 | B6: Barratt & Oke | C6: 2007 | D6: Global | E6: Journal | F6: Empirical, RBV | G6: Antecedents of supply chain visibility | H6: Visibility | I6: Y | J6: JOM 25(6)
A7: Waller 2013 | B7: Waller & Fawcett | C7: 2013 | D7: Global | E7: Journal | F7: Editorial review | G7: Data science transforms supply chain design | H7: Analytics value | I7: Y | J7: 10.1111/jbl.12010
A8: Few 2013 | B8: Few | C8: 2013 | D8: Global | E8: Book | F8: Design principles | G8: At a glance dashboard design | H8: Dashboard design | I8: Y | J8: Analytics Press
A9: Brusset 2016 | B9: Brusset | C9: 2016 | D9: Global | E9: Journal | F9: Empirical | G9: Visibility enhances agility | H9: Visibility, agility | I9: Y | J9: IJPE 171
A10: Wang 2016 | B10: Wang, Gunasekaran, Ngai & Papadopoulos | C10: 2016 | D10: Global | E10: Journal | F10: Review | G10: Big data analytics in logistics and SCM | H10: Analytics adoption | I10: Y | J10: IJPE 176
A11: APICS 2017 | B11: APICS (SCOR v12.0) | C11: 2017 | D11: Global | E11: Standard | F11: Reference model | G11: Standard supply chain metrics | H11: Perfect order, reliability | I11: Y | J11: SCOR 12.0
A12: Trzuskawska 2017 | B12: Trzuskawska-Grzesinska | C12: 2017 | D12: Global | E12: Journal | F12: Conceptual | G12: Control tower past and future | H12: Control tower model | I12: Y | J12: JEM 27(1)
A13: Buyukozkan 2018 | B13: Buyukozkan & Gocer | C13: 2018 | D13: Global | E13: Journal | F13: Review | G13: Digital supply chain framework | H13: Digital maturity | I13: Y | J13: 10.1016/j.compind.2018.02.010
A14: Nguyen 2018 | B14: Nguyen, Zhou, Spiegler, Ieromonachou & Lin | C14: 2018 | D14: Global | E14: Journal | F14: Review | G14: State of the art of big data analytics in SCM | H14: Analytics classification | I14: Y | J14: 10.1016/j.cor.2017.07.004
A15: Olist 2018 | B15: Olist | C15: 2018 | D15: Global | E15: Dataset | F15: Open data | G15: Brazilian e-commerce order timestamps | H15: Delivery timeliness | I15: Y | J15: kaggle olistbr
... A25: World Bank 2023 | B25: World Bank | C25: 2023 | D25: Global | E25: Report | F25: Index report | G25: Connecting to Compete LPI 2023 | H25: Global benchmark | I25: Y | J25: lpi.worldbank.org
A27: Included count | C27: =COUNTA(A4:A25) -> 22

Sheet 04_Cleaning_Log
A1: Cleaning Log — DataCo extract (template)
A2: Records each cleaning decision for reproducibility. Row counts are illustrative placeholders to be filled on the live extract.
A3: Step | B3: Field | C3: Issue | D3: Action | E3: Rows affected | F3: Before example | G3: After example | H3: Status
A4: 1 | B4: Encoding | C4: File uses a Latin character set | D4: Load with latin-1 encoding | E4: All | F4: Mojibake text | G4: Clean text | H4: Done
A5: 2 | B5: order date | C5: Stored as text | D5: Parse to date type | E5: All | F5: 01-02-2017 text | G5: 2017-02-01 date | H5: Done
A6: 3 | B6: Delivery delay | C6: Not present | D6: Derive real minus scheduled days | E6: All | F6: n/a | G6: delay column | H6: Done
A7: 4 | B7: Delivery delay | C7: Impossible negative beyond early limit | D7: Flag and review | E7: 12 | F7: -40 | G7: flagged | H7: Done
A8: 5 | B8: Status | C8: Canceled mixed with delivered | D8: Separate canceled orders | E8: Canceled set | F8: mixed | G8: split | H8: Done
A9: 6 | B9: Order Item Id | C9: Duplicate lines | D9: Drop duplicates on key | E9: 31 | F9: 2 copies | G9: 1 row | H9: Done
A10: 7 | B10: Region / Category | C10: Case and spelling differ | D10: Standardise text | E10: All | F10: latam | G10: LATAM | H10: Done
A11: 8 | B11: Order City / Zip | C11: Missing values | D11: Apply rule and log | E11: 240 | F11: blank | G11: Unknown tag | H11: Done
A12: 9 | B12: Sales / Profit | C12: Outliers | D12: Check real or error | E12: 18 | F12: 99999 | G12: verified | H12: Done
A13: 10 | B13: OTIF flag | C13: Not present | D13: Derive on time and in full | E13: All | F13: n/a | G13: OTIF 0 or 1 | H13: Done
A14: 11 | B14: Schema | C14: Flat file | D14: Build star schema | E14: All | F14: one table | G14: fact and dims | H14: Done
A15: 12 | B15: Audit | C15: No record | D15: Save this log | E15: All | F15: n/a | G15: logged | H15: Done
B17: Steps complete | E17: =COUNTIF(H4:H15,"Done") -> 12

Sheet 05_Analysis
A1: Analysis — KPI engine
A2: Rows 4 to 27 are an illustrative sample for formula demonstration. Replace with the cleaned DataCo extract. KPI cells update automatically.
A3: OrderID | B3: Region | C3: Category | D3: ShipMode | E3: Status | F3: DelayDays | G3: Sales | H3: QtyOrd | I3: QtyDel | J3: OTIF | L3: KPI | M3: Value | O3: Assumptions
A4: O1001 | B4: LATAM | C4: Cleats | D4: Standard Class | E4: Late delivery | F4: 3 | G4: 299 | H4: 4 | I4: 4 | J4: =IF(AND(OR(E4="On time",E4="Advance"),I4>=H4),1,0) -> 0 | L4: Total orders | M4: =COUNTA(A4:A27) -> 24 | O4: Order accuracy | P4: 0.98
A5: O1002 | B5: Europe | C5: Electronics | D5: First Class | E5: On time | F5: 0 | G5: 540 | H5: 2 | I5: 2 | J5: =IF(AND(OR(E5="On time",E5="Advance"),I5>=H5),1,0) -> 1 | L5: Canceled orders | M5: =COUNTIF(E4:E27,"Shipping canceled") -> 2 | O5: Undamaged rate | P5: 0.99
A6: O1003 | B6: Pacific Asia | C6: Apparel | D6: Standard Class | E6: Late delivery | F6: 2 | G6: 120 | H6: 5 | I6: 5 | J6: =IF(AND(OR(E6="On time",E6="Advance"),I6>=H6),1,0) -> 0 | L6: Delivered base | M6: =M4-M5 -> 22 | O6: Correct documents | P6: 0.99
A7: O1004 | B7: USCA | C7: Cardio Equipment | D7: Second Class | E7: Advance | F7: -1 | G7: 1500 | H7: 1 | I7: 1 | J7: =IF(AND(OR(E7="On time",E7="Advance"),I7>=H7),1,0) -> 1 | L7: Late orders | M7: =COUNTIF(E4:E27,"Late delivery") -> 9
A8: O1005 | B8: LATAM | C8: Electronics | D8: Standard Class | E8: Late delivery | F8: 4 | G8: 760 | H8: 3 | I8: 2 | J8: =IF(AND(OR(E8="On time",E8="Advance"),I8>=H8),1,0) -> 0 | L8: Late delivery rate | M8: =IFERROR(M7/M6,0) -> 0.40909091
A9: O1006 | B9: Europe | C9: Apparel | D9: Same Day | E9: On time | F9: 0 | G9: 90 | H9: 6 | I9: 6 | J9: =IF(AND(OR(E9="On time",E9="Advance"),I9>=H9),1,0) -> 1 | L9: OTIF orders | M9: =SUM(J4:J27) -> 12
A10: O1007 | B10: Pacific Asia | C10: Cleats | D10: Standard Class | E10: On time | F10: 0 | G10: 210 | H10: 4 | I10: 4 | J10: =IF(AND(OR(E10="On time",E10="Advance"),I10>=H10),1,0) -> 1 | L10: OTIF rate | M10: =IFERROR(M9/M6,0) -> 0.54545455
A11: O1008 | B11: USCA | C11: Electronics | D11: First Class | E11: Late delivery | F11: 1 | G11: 980 | H11: 2 | I11: 2 | J11: =IF(AND(OR(E11="On time",E11="Advance"),I11>=H11),1,0) -> 0 | L11: Average delay (days) | M11: =AVERAGEIFS(F4:F27,E4:E27,"<>Shipping canceled") -> 0.90909091
A12: O1009 | B12: LATAM | C12: Apparel | D12: Second Class | E12: Advance | F12: -2 | G12: 150 | H12: 3 | I12: 3 | J12: =IF(AND(OR(E12="On time",E12="Advance"),I12>=H12),1,0) -> 1 | L12: Sales at risk (late) | M12: =SUMIF(E4:E27,"Late delivery",G4:G27) -> 6504
A13: O1010 | B13: Europe | C13: Cardio Equipment | D13: Standard Class | E13: Late delivery | F13: 5 | G13: 2100 | H13: 1 | I13: 1 | J13: =IF(AND(OR(E13="On time",E13="Advance"),I13>=H13),1,0) -> 0 | L13: Total sales | M13: =SUM(G4:G27) -> 16984
A14: O1011 | B14: Pacific Asia | C14: Electronics | D14: Standard Class | E14: On time | F14: 0 | G14: 430 | H14: 2 | I14: 2 | J14: =IF(AND(OR(E14="On time",E14="Advance"),I14>=H14),1,0) -> 1 | L14: Fill rate | M14: =IFERROR(SUM(I4:I27)/SUM(H4:H27),0) -> 0.92857143
A15: O1012 | B15: USCA | C15: Cleats | D15: Same Day | E15: On time | F15: 0 | G15: 260 | H15: 4 | I15: 3 | J15: =IF(AND(OR(E15="On time",E15="Advance"),I15>=H15),1,0) -> 0 | L15: Perfect order proxy | M15: =M10*P4*P5*P6 -> 0.523908
A16: O1013 | B16: LATAM | C16: Cardio Equipment | D16: Standard Class | E16: Late delivery | F16: 2 | G16: 1750 | H16: 1 | I16: 1 | J16: =IF(AND(OR(E16="On time",E16="Advance"),I16>=H16),1,0) -> 0
A17: O1014 | B17: Europe | C17: Electronics | D17: Second Class | E17: On time | F17: 0 | G17: 615 | H17: 2 | I17: 2 | J17: =IF(AND(OR(E17="On time",E17="Advance"),I17>=H17),1,0) -> 1
A18: O1015 | B18: Pacific Asia | C18: Apparel | D18: Standard Class | E18: Late delivery | F18: 6 | G18: 180 | H18: 5 | I18: 4 | J18: =IF(AND(OR(E18="On time",E18="Advance"),I18>=H18),1,0) -> 0
A19: O1016 | B19: USCA | C19: Apparel | D19: First Class | E19: Advance | F19: -1 | G19: 130 | H19: 3 | I19: 3 | J19: =IF(AND(OR(E19="On time",E19="Advance"),I19>=H19),1,0) -> 1
A20: O1017 | B20: LATAM | C20: Electronics | D20: Standard Class | E20: On time | F20: 0 | G20: 845 | H20: 2 | I20: 2 | J20: =IF(AND(OR(E20="On time",E20="Advance"),I20>=H20),1,0) -> 1
A21: O1018 | B21: Europe | C21: Cleats | D21: Standard Class | E21: Late delivery | F21: 3 | G21: 220 | H21: 4 | I21: 4 | J21: =IF(AND(OR(E21="On time",E21="Advance"),I21>=H21),1,0) -> 0
A22: O1019 | B22: Pacific Asia | C22: Cardio Equipment | D22: Second Class | E22: Shipping canceled | G22: 1990 | H22: 1 | I22: 0 | J22: =IF(AND(OR(E22="On time",E22="Advance"),I22>=H22),1,0) -> 0
A23: O1020 | B23: USCA | C23: Electronics | D23: Standard Class | E23: On time | F23: 0 | G23: 720 | H23: 2 | I23: 2 | J23: =IF(AND(OR(E23="On time",E23="Advance"),I23>=H23),1,0) -> 1
A24: O1021 | B24: LATAM | C24: Apparel | D24: Same Day | E24: Late delivery | F24: 1 | G24: 95 | H24: 6 | I24: 6 | J24: =IF(AND(OR(E24="On time",E24="Advance"),I24>=H24),1,0) -> 0
A25: O1022 | B25: Europe | C25: Electronics | D25: First Class | E25: On time | F25: 0 | G25: 560 | H25: 2 | I25: 2 | J25: =IF(AND(OR(E25="On time",E25="Advance"),I25>=H25),1,0) -> 1
A26: O1023 | B26: Pacific Asia | C26: Cleats | D26: Standard Class | E26: Advance | F26: -3 | G26: 240 | H26: 4 | I26: 4 | J26: =IF(AND(OR(E26="On time",E26="Advance"),I26>=H26),1,0) -> 1
A27: O1024 | B27: USCA | C27: Cardio Equipment | D27: Standard Class | E27: Shipping canceled | G27: 2200 | H27: 1 | I27: 0 | J27: =IF(AND(OR(E27="On time",E27="Advance"),I27>=H27),1,0) -> 0
A30: Region performance
A31: Region | B31: Orders | C31: Late orders | D31: Late rate | E31: Sales
A32: LATAM | B32: =COUNTIF($B$4:$B$27,A32) -> 6 | C32: =COUNTIFS($B$4:$B$27,A32,$E$4:$E$27,"Late delivery") -> 4 | D32: =IFERROR(C32/B32,0) -> 0.66666667 | E32: =SUMIF($B$4:$B$27,A32,$G$4:$G$27) -> 3899
A33: Europe | B33: =COUNTIF($B$4:$B$27,A33) -> 6 | C33: =COUNTIFS($B$4:$B$27,A33,$E$4:$E$27,"Late delivery") -> 2 | D33: =IFERROR(C33/B33,0) -> 0.33333333 | E33: =SUMIF($B$4:$B$27,A33,$G$4:$G$27) -> 4125
A34: Pacific Asia | B34: =COUNTIF($B$4:$B$27,A34) -> 6 | C34: =COUNTIFS($B$4:$B$27,A34,$E$4:$E$27,"Late delivery") -> 2 | D34: =IFERROR(C34/B34,0) -> 0.33333333 | E34: =SUMIF($B$4:$B$27,A34,$G$4:$G$27) -> 3170
A35: USCA | B35: =COUNTIF($B$4:$B$27,A35) -> 6 | C35: =COUNTIFS($B$4:$B$27,A35,$E$4:$E$27,"Late delivery") -> 1 | D35: =IFERROR(C35/B35,0) -> 0.16666667 | E35: =SUMIF($B$4:$B$27,A35,$G$4:$G$27) -> 5790
A36: Total | B36: =SUM(B32:B35) -> 24 | C36: =SUM(C32:C35) -> 9 | D36: =IFERROR(C36/B36,0) -> 0.375 | E36: =SUM(E32:E35) -> 16984

Sheet 06_PRISMA
A1: PRISMA flow
A2: PRISMA tracks records from identification to inclusion. Counts below are the project record. The included count is checked against the extraction table.
A3: Stage | B3: Count | C3: Formula or note
A4: Records identified through databases | B4: 168 | C4: Sum of database hits
A5: Records identified through other sources | B5: 14 | C5: Reports and grey literature
A6: Duplicates removed | B6: 22 | C6: Same record across sources
A7: Records screened | B7: =B4+B5-B6 -> 160 | C7: Identified minus duplicates
A8: Records excluded at title and abstract | B8: 112 | C8: Off topic or low quality
A9: Full text assessed for eligibility | B9: =B7-B8 -> 48 | C9: Screened minus excluded
A10: Full text excluded | B10: 26 | C10: See reasons below
A11: Studies included | B11: =B9-B10 -> 22 | C11: Assessed minus excluded
A13: Extraction table rows | B13: =COUNTA('03_Extraction'!A4:A25) -> 22
A14: Consistency check | B14: =IF(B11=B13,"MATCH","CHECK") -> MATCH
A16: Exclusion reasons (full text stage)
A17: Reason | B17: Count
A18: Not peer reviewed or non primary | B18: 10
A19: Duplicate record | B19: 4
A20: Out of scope topic | B20: 7
A21: Source quality concern | B21: 5
A22: Total excluded | B22: =SUM(B18:B21) -> 26

Sheet 07_Bibliometric
A1: Bibliometric analysis
A2: Counts are computed from the extraction table. Bibliometric analysis maps output by year, source type, and evidence level.
A3: Publications by period | D3: Publications by type
A4: Period | B4: Count | D4: Type | E4: Count
A5: 1990 to 2010 | B5: =COUNTIFS('03_Extraction'!$C$4:$C$25,"<=2010") -> 3 | D5: Journal | E5: =COUNTIF('03_Extraction'!$E$4:$E$25,"Journal") -> 13
A6: 2011 to 2015 | B6: =COUNTIFS('03_Extraction'!$C$4:$C$25,">=2011",'03_Extraction'!$C$4:$C$25,"<=2015") -> 2 | D6: Report | E6: =COUNTIF('03_Extraction'!$E$4:$E$25,"Report") -> 5
A7: 2016 to 2018 | B7: =COUNTIFS('03_Extraction'!$C$4:$C$25,">=2016",'03_Extraction'!$C$4:$C$25,"<=2018") -> 7 | D7: Dataset | E7: =COUNTIF('03_Extraction'!$E$4:$E$25,"Dataset") -> 2
A8: 2019 to 2021 | B8: =COUNTIFS('03_Extraction'!$C$4:$C$25,">=2019",'03_Extraction'!$C$4:$C$25,"<=2021") -> 4 | D8: Standard | E8: =COUNTIF('03_Extraction'!$E$4:$E$25,"Standard") -> 1
A9: 2022 to 2023 | B9: =COUNTIFS('03_Extraction'!$C$4:$C$25,">=2022",'03_Extraction'!$C$4:$C$25,"<=2023") -> 6 | D9: Book | E9: =COUNTIF('03_Extraction'!$E$4:$E$25,"Book") -> 1
A10: Total | B10: =SUM(B5:B9) -> 22 | D10: Total | E10: =SUM(E5:E9) -> 22
A12: Evidence by level
A13: Level | B13: Count
A14: Global | B14: =COUNTIF('03_Extraction'!$D$4:$D$25,"Global") -> 17
A15: National | B15: =COUNTIF('03_Extraction'!$D$4:$D$25,"National") -> 3
A16: State | B16: =COUNTIF('03_Extraction'!$D$4:$D$25,"State") -> 1
A17: Local | B17: =COUNTIF('03_Extraction'!$D$4:$D$25,"Local") -> 1
A18: Total | B18: =SUM(B14:B17) -> 22
A20: Interpretation. The corpus concentrates in 2016 to 2023, which reflects the rise of supply chain analytics and the COVID period. Journal articles dominate, supported by official reports for the India levels.

Sheet 08_N_gram
A1: N gram keyword analysis
A2: N gram analysis counts how often terms appear across the corpus. Column A lists the included titles. The term table counts titles that contain each term using COUNTIF with wildcards. Full unigram and bigram analysis is run in Python with a tokeniser and a stopword list.
A3: Included titles | C3: Term (unigram / bigram) | D3: Frequency
A4: information distortion in a supply chain the bullwhip effect | C4: supply chain | D4: =COUNTIF($A$4:$A$25,"*supply chain*") -> 15
A5: performance measures and metrics in a supply chain environment | C5: big data | D5: =COUNTIF($A$4:$A$25,"*big data*") -> 5
A6: antecedents of supply chain visibility in retail supply chains | C6: analytics | D6: =COUNTIF($A$4:$A$25,"*analytics*") -> 4
A7: data science predictive analytics and big data supply chain | C7: visibility | D7: =COUNTIF($A$4:$A$25,"*visibility*") -> 3
A8: information dashboard design displaying data at a glance | C8: logistics | D8: =COUNTIF($A$4:$A$25,"*logistics*") -> 5
A9: does supply chain visibility enhance agility | C9: performance | D9: =COUNTIF($A$4:$A$25,"*performance*") -> 4
A10: big data analytics in logistics and supply chain management | C10: digital | D10: =COUNTIF($A$4:$A$25,"*digital*") -> 2
A11: supply chain operations reference scor model | C11: resilience | D11: =COUNTIF($A$4:$A$25,"*resilience*") -> 2
A12: control towers in supply chain management past and future | C12: forecasting | D12: =COUNTIF($A$4:$A$25,"*forecasting*") -> 1
A13: digital supply chain literature review and a proposed framework | C13: delivery | D13: =COUNTIF($A$4:$A$25,"*delivery*") -> 2
A14: big data analytics in supply chain management a state of the art review | C14: disruption | D14: =COUNTIF($A$4:$A$25,"*disruption*") -> 2
A15: brazilian e-commerce public dataset orders and delivery | C15: dashboard | D15: =COUNTIF($A$4:$A$25,"*dashboard*") -> 1
A16: dataco smart supply chain for big data analysis | C16: index | D16: =COUNTIF($A$4:$A$25,"*index*") -> 2
A17: predicting the impacts of epidemic outbreaks on global supply chains
A18: Reading. The term supply chain appears most often, which confirms the topical core. Big data, analytics, and visibility cluster around the control tower theme. Resilience and disruption mark the COVID era literature.
A19: a digital supply chain twin for managing disruption risks and resilience
A20: national logistics policy reducing logistics cost
A21: machine learning demand forecasting and supply chain performance
A22: logistics ease across different states report
A23: last mile strategies for urban freight delivery a systematic review
A24: india ranks on the world bank logistics performance index
A25: connecting to compete trade logistics performance index

Sheet 09_Formula_Sheet
A1: Formula library
A2: Each required function with exact syntax, a live result, and a plain explanation. XLOOKUP, UNIQUE, FILTER, and LET show Excel 365 syntax; the live demo uses a supported equivalent so a value always appears.
A3: Mini lookup table | E3: Sales sample
A4: ProductID | B4: Category | C4: UnitPrice | E4: Cat | F4: Sales
A5: P01 | B5: Cleats | C5: 75 | E5: Cleats | F5: 299
A6: P02 | B6: Electronics | C6: 320 | E6: Electronics | F6: 760
A7: P03 | B7: Apparel | C7: 40 | E7: Apparel | F7: 120
A8: P04 | B8: Cardio Equipment | C8: 1500 | E8: Electronics | F8: 980
A9: P05 | B9: Helmets | C9: 60 | E9: Cleats | F9: 210
A12: Function reference
A13: Function | B13: Syntax example | C13: Live result | D13: Plain explanation
A14: IF | B14: IF(F5>500,"High","Low") | C14: =IF(F5>500,"High","Low") -> Low | D14: Returns one value when a test is true and another when false.
A15: COUNTIF | B15: COUNTIF(E5:E9,"Electronics") | C15: =COUNTIF(E5:E9,"Electronics") -> 2 | D15: Counts cells in a range that meet one condition.
A16: COUNTIFS | B16: COUNTIFS(E5:E9,"Cleats",F5:F9,">200") | C16: =COUNTIFS(E5:E9,"Cleats",F5:F9,">200") -> 2 | D16: Counts rows that meet several conditions at once.
A17: SUMIF | B17: SUMIF(E5:E9,"Electronics",F5:F9) | C17: =SUMIF(E5:E9,"Electronics",F5:F9) -> 1740 | D17: Adds values where a single condition holds.
A18: SUMIFS | B18: SUMIFS(F5:F9,E5:E9,"Cleats") | C18: =SUMIFS(F5:F9,E5:E9,"Cleats") -> 509 | D18: Adds values where several conditions hold.
A19: INDEX + MATCH | B19: INDEX(B5:B9,MATCH("P03",A5:A9,0)) | C19: =INDEX(B5:B9,MATCH("P03",A5:A9,0)) -> Apparel | D19: Looks up a value by matching a key. Works in every version.
A20: TEXTJOIN | B20: TEXTJOIN(" | ",TRUE,A5,B5,C5) | C20: =A5&" | "&B5&" | "&C5 -> P01 | Cleats | 75 | D20: Joins fields into one labelled key. Live demo uses the & operator because some engines lack TEXTJOIN.
A21: XLOOKUP | B21: XLOOKUP("P03",A5:A9,B5:B9) | C21: =INDEX(B5:B9,MATCH("P03",A5:A9,0)) -> Apparel | D21: Excel 365 lookup. Finds a key and returns a matched value. Live demo uses INDEX MATCH.
A22: UNIQUE | B22: UNIQUE(E5:E9) | C22: =SUMPRODUCT(1/COUNTIF(E5:E9,E5:E9)) -> 3 | D22: Excel 365 returns the distinct list. Live demo counts how many distinct categories exist.
A23: FILTER | B23: FILTER(E5:F9,F5:F9>500) | C23: =COUNTIF(F5:F9,">500") -> 2 | D23: Excel 365 returns only rows that pass a test. Live demo counts how many rows pass.
A24: LET | B24: LET(d,F5-F6,IF(d>0,"up","down")) | C24: =IF((F5-F6)>0,"up","down") -> down | D24: Excel 365 names a value once then reuses it. Live demo shows the same logic.
A25: Pivot summary | B25: PivotTable: rows Category, values Sum of Sales | C25: =SUMIF(E5:E9,"Electronics",F5:F9) -> 1740 | D25: A pivot table groups and totals data. The SUMIF here gives the same group total without a pivot.

Sheet 10_References
A1: References (APA 7)
A2: Full bibliography with type, level, verification status, and link. All sources were checked against a primary record.
A3: Key | B3: APA 7 citation | C3: Type | D3: Level | E3: Verified | F3: Link / DOI
A4: Lee 1997 | B4: Lee, H. L., Padmanabhan, V., & Whang, S. (1997). Information distortion in a supply chain: The bullwhip effect. Management Science, 43(4), 546-558. | C4: Journal | D4: Global | E4: Y | F4: 10.1287/mnsc.43.4.546
A5: Gunasekaran 2001 | B5: Gunasekaran, A., Patel, C., & Tirtiroglu, E. (2001). Performance measures and metrics in a supply chain environment. IJOPM, 21(1/2), 71-87. | C5: Journal | D5: Global | E5: Y | F5: IJOPM 21(1/2)
A6: Barratt 2007 | B6: Barratt, M., & Oke, A. (2007). Antecedents of supply chain visibility in retail supply chains. Journal of Operations Management, 25(6), 1217-1233. | C6: Journal | D6: Global | E6: Y | F6: JOM 25(6)
A7: Waller 2013 | B7: Waller, M. A., & Fawcett, S. E. (2013). Data science, predictive analytics, and big data. Journal of Business Logistics, 34(2), 77-84. | C7: Journal | D7: Global | E7: Y | F7: 10.1111/jbl.12010
A8: Few 2013 | B8: Few, S. (2013). Information dashboard design (2nd ed.). Analytics Press. | C8: Book | D8: Global | E8: Y | F8: Analytics Press
A9: Brusset 2016 | B9: Brusset, X. (2016). Does supply chain visibility enhance agility? International Journal of Production Economics, 171, 46-59. | C9: Journal | D9: Global | E9: Y | F9: IJPE 171
A10: Wang 2016 | B10: Wang, G., Gunasekaran, A., Ngai, E. W. T., & Papadopoulos, T. (2016). Big data analytics in logistics and supply chain management. IJPE, 176, 98-110. | C10: Journal | D10: Global | E10: Y | F10: IJPE 176
A11: APICS 2017 | B11: APICS. (2017). Supply Chain Operations Reference (SCOR) model, version 12.0. APICS. | C11: Standard | D11: Global | E11: Y | F11: SCOR 12.0
A12: Trzuskawska 2017 | B12: Trzuskawska-Grzesinska, A. (2017). Control towers in supply chain management: Past and future. Journal of Economics and Management, 27(1), 114-133. | C12: Journal | D12: Global | E12: Y | F12: JEM 27(1)
A13: Buyukozkan 2018 | B13: Buyukozkan, G., & Gocer, F. (2018). Digital supply chain: Literature review and a proposed framework. Computers in Industry, 97, 157-177. | C13: Journal | D13: Global | E13: Y | F13: 10.1016/j.compind.2018.02.010
A14: Nguyen 2018 | B14: Nguyen, T., Zhou, L., Spiegler, V., Ieromonachou, P., & Lin, Y. (2018). Big data analytics in supply chain management. Computers & Operations Research, 98, 254-264. | C14: Journal | D14: Global | E14: Y | F14: 10.1016/j.cor.2017.07.004
... A25: World Bank 2023 | B25: World Bank. (2023). Connecting to compete 2023: Trade logistics in an uncertain global economy. The World Bank. | C25: Report | D25: Global | E25: Y | F25: lpi.worldbank.org
A27: Total references | C27: =COUNTA(A4:A25) -> 22
A28: Verified | C28: =COUNTIF(E4:E25,"Y") -> 22

Sheet 11_Final_Summary
A1: Final Summary — Project 1
A2: One page status view. KPI figures link live to the analysis sheet. Reference counts link to the references sheet.
A4: Project | B4: Supply Chain Control Tower Dashboard
A5: Core question | B5: What drives late delivery and can high risk orders be flagged before dispatch
A6: Primary dataset | B6: DataCo Smart Supply Chain (Constante, Silva & Pereira, 2019)
A8: Headline KPIs (illustrative sample) | C8: Value
A9: Late delivery rate | C9: ='05_Analysis'!M8 -> 0.40909091
A10: OTIF rate | C10: ='05_Analysis'!M10 -> 0.54545455
A11: Average delay (days) | C11: ='05_Analysis'!M11 -> 0.90909091
A12: Fill rate | C12: ='05_Analysis'!M14 -> 0.92857143
A13: Sales at risk (late) | C13: ='05_Analysis'!M12 -> 6504
A15: Evidence base | C15: Count
A16: Total references | C16: =COUNTA('10_References'!A4:A25) -> 22
A17: Verified references | C17: =COUNTIF('10_References'!E4:E25,"Y") -> 22
A18: Studies included (PRISMA) | C18: ='06_PRISMA'!B11 -> 22
A20: Status checklist
A21: Search logged | C21: Done
A22: Screening complete | C22: Done
A23: Extraction complete | C23: Done
A24: PRISMA consistent | C24: Done
A25: Bibliometric done | C25: Done
A26: N gram done | C26: Done
A27: KPIs computing | C27: Done
A28: References verified | C28: Done
